charter_compiler/__init__.py
charter_compiler/analysis/loop_optimizer.py
charter_compiler/analysis/memoization.py
charter_compiler/analysis/pattern_detector.py
charter_compiler/analysis/prefix_analyzer.py
charter_compiler/api.py
charter_compiler/compiler.py
charter_compiler/config/priority_mapper.py
charter_compiler/config/trtllm_config.py
charter_compiler/configs/benchmarks.yaml
charter_compiler/configs/default.yaml
charter_compiler/dag/builder.py
charter_compiler/executor/__init__.py
charter_compiler/executor/cache_manager.py
charter_compiler/executor/orchestrator.py
charter_compiler/executor/scheduler.py
charter_compiler/executor/triton_client.py
charter_compiler/executor/triton_client_production.py
charter_compiler/models.py
charter_compiler/monitor/metrics.py
charter_compiler/parser/ast_parser.py
charter_compiler/version.py
charter_compiler-0.1.0.dist-info/METADATA
charter_compiler-0.1.0.dist-info/WHEEL
charter_compiler-0.1.0.dist-info/licenses/LICENSE
charter_compiler-0.1.0.dist-info/RECORD
